{
    "mode": "Indexed",
    "policyRule": {
      "if": {
        "allOf": [
          {
            "field": "type",
            "equals": "Microsoft.KeyVault/vaults"
          },
          {
            "anyOf": [
              {
                "field": "Microsoft.KeyVault/vaults/networkAcls.defaultAction",
                "notEquals": "Deny"
              },
              {
                "field": "Microsoft.KeyVault/vaults/networkAcls.virtualNetworkRules[*].id",
                "exists": "false"
              }
            ]
          }
        ]
      },
      "then": {
        "effect": "[parameters('effect')]"
      }
    },
    "parameters": {
      "effect": {
        "type": "String",
        "metadata": {
          "displayName": "Effect",
          "description": "Enable or disable the execution of the policy"
        },
        "allowedValues": [
          "Audit",
          "Disabled"
        ],
        "defaultValue": "Audit"
      }
    }
  }